PyCaliper/setup.py
pycaliper-1.0.8.dist-info/licenses/LICENSE
pycaliper-1.0.8.dist-info/METADATA
pycaliper-1.0.8.dist-info/WHEEL
pycaliper-1.0.8.dist-info/top_level.txt
pycaliper-1.0.8.dist-info/RECORD
