Metadata-Version: 2.4
Name: PyCaliper
Version: 1.0.8
Summary: A unit of measure project.
Author: Kent Randall
Author-email: Kent Randall <point85.llc@gmail.com>
Project-URL: Homepage, https://github.com/point85/PyCaliper
Project-URL: Issues, https://github.com/point85/PyCaliper/issues
Keywords: units of measure,units,measurement units,uom,units of measurement,measure-conversion
Classifier: Programming Language :: Python :: 3
Classifier: License :: OSI Approved :: MIT License
Classifier: Operating System :: OS Independent
Requires-Python: >=3.1
License-File: LICENSE
Dynamic: author
Dynamic: license-file
